pywalletconnectv1/__init__.py
pywalletconnectv1/wc_cipher.py
pywalletconnectv1/wc_client.py
pywalletconnectv1/wc_session_store.py
pywalletconnectv1/wc_session_store_item.py
pywalletconnectv1/wc_session_store_type.py
pywalletconnectv1/exceptions/__init__.py
pywalletconnectv1/exceptions/wc_exceptions.py
pywalletconnectv1/jsonrpc/__init__.py
pywalletconnectv1/jsonrpc/json_rpc_error.py
pywalletconnectv1/jsonrpc/json_rpc_request.py
pywalletconnectv1/jsonrpc/json_rpc_response.py
pywalletconnectv1/models/__init__.py
pywalletconnectv1/models/wc_account.py
pywalletconnectv1/models/wc_encryption_payload.py
pywalletconnectv1/models/wc_method.py
pywalletconnectv1/models/wc_peer_meta.py
pywalletconnectv1/models/wc_socket_message.py
pywalletconnectv1/models/ethereum/__init__.py
pywalletconnectv1/models/ethereum/wc_ethereum_sign_message.py
pywalletconnectv1/models/ethereum/wc_ethereum_switch_chain.py
pywalletconnectv1/models/ethereum/wc_ethereum_transaction.py
pywalletconnectv1/models/session/__init__.py
pywalletconnectv1/models/session/wc_approve_session_response.py
pywalletconnectv1/models/session/wc_session.py
pywalletconnectv1/models/session/wc_session_request.py
pywalletconnectv1/models/session/wc_session_update.py
pywalletconnectv1-0.1.2.dist-info/LICENSE
pywalletconnectv1-0.1.2.dist-info/METADATA
pywalletconnectv1-0.1.2.dist-info/WHEEL
pywalletconnectv1-0.1.2.dist-info/top_level.txt
pywalletconnectv1-0.1.2.dist-info/RECORD
