Metadata-Version: 2.1
Name: pywalletconnectv1
Version: 0.1.2
Summary: Simple python library that implements WalletConnect protocol v1
Home-page: https://github.com/Toporin/pywalletconnectv1
Author: Toporin
Author-email: satochip.wallet@gmail.com
License: UNKNOWN
Project-URL: Github, https://github.com/Toporin
Project-URL: Webshop, https://satochip.io/
Project-URL: Telegram, https://t.me/Satochip
Project-URL: Twitter, https://twitter.com/satochipwallet
Project-URL: Source, https://github.com/Toporin/pywalletconnectv1/
Project-URL: Tracker, https://github.com/Toporin/pywalletconnectv1/issues
Platform: UNKNOWN
Classifier: Programming Language :: Python :: 3
Classifier: License :: OSI Approved :: GNU Lesser General Public License v3 (LGPLv3)
Classifier: Operating System :: OS Independent
Requires-Python: >=3.6
Requires-Dist: ecdsa (>=0.15)
Requires-Dist: pyaes (>=1.6.1)
Requires-Dist: pykson (>=0.9.9.8.7)
Requires-Dist: websocket-client (>=1.3.1)
Requires-Dist: certifi
